batchqueue/BatchQueue.py
batchqueue/__init__.py
batchqueue-0.1.0.dist-info/LICENSE.mit
batchqueue-0.1.0.dist-info/METADATA
batchqueue-0.1.0.dist-info/WHEEL
batchqueue-0.1.0.dist-info/top_level.txt
batchqueue-0.1.0.dist-info/RECORD
