Metadata-Version: 2.1
Name: batchqueue
Version: 0.1.0
Summary: A Queue type for handling traffic that arrives in bursts
Home-page: https://github.com/sgallagher/BatchQueue
Author: Stephen Gallagher
Author-email: sgallagh@redhat.com
License: MIT
Keywords: queue,batch
Platform: any
Classifier: License :: OSI Approved :: MIT License
Classifier: Programming Language :: Python :: 3
Classifier: Development Status :: 4 - Beta
Classifier: Operating System :: MacOS :: MacOS X
Classifier: Operating System :: Microsoft :: Windows
Classifier: Operating System :: POSIX :: Linux
Classifier: Operating System :: OS Independent
Classifier: Intended Audience :: Developers
Classifier: Topic :: Software Development :: Libraries :: Python Modules
License-File: LICENSE.mit
